tweet_hub_sdk/__init__.py
tweet_hub_sdk/tweet_hub_client.py
tweet_hub_sdk-0.0.1.dist-info/METADATA
tweet_hub_sdk-0.0.1.dist-info/WHEEL
tweet_hub_sdk-0.0.1.dist-info/entry_points.txt
tweet_hub_sdk-0.0.1.dist-info/licenses/LICENSE-CODE
tweet_hub_sdk-0.0.1.dist-info/RECORD
