Metadata-Version: 2.4
Name: tweet_hub_sdk
Version: 0.0.1
Summary: tweet_hub_sdk
License:     MIT License
License-File: LICENSE-CODE
Classifier: License :: OSI Approved :: MIT License
Classifier: Operating System :: OS Independent
Classifier: Programming Language :: Python :: 3
Requires-Python: >=3.12
